scl_loader/__init__.py
scl_loader/scl_loader.py
scl_loader/resources/SCL_Schema/SCL.xsd
scl_loader/resources/SCL_Schema/SCL_BaseSimpleTypes.xsd
scl_loader/resources/SCL_Schema/SCL_BaseTypes.xsd
scl_loader/resources/SCL_Schema/SCL_Communication.xsd
scl_loader/resources/SCL_Schema/SCL_DataTypeTemplates.xsd
scl_loader/resources/SCL_Schema/SCL_Enums.xsd
scl_loader/resources/SCL_Schema/SCL_IED.xsd
scl_loader/resources/SCL_Schema/SCL_Substation.xsd
scl_loader-1.11.7.dist-info/LICENSE
scl_loader-1.11.7.dist-info/METADATA
scl_loader-1.11.7.dist-info/WHEEL
scl_loader-1.11.7.dist-info/top_level.txt
scl_loader-1.11.7.dist-info/RECORD
