Metadata-Version: 2.1
Name: scl_loader
Version: 1.11.7
Summary: Outil de manipulation de SCD
Classifier: License :: OSI Approved :: Apache Software License
Classifier: Programming Language :: Python :: 3
Classifier: Programming Language :: Python :: 3.6
Requires-Python: >=3.6, <4
License-File: LICENSE
Requires-Dist: lxml
Requires-Dist: pytest
Requires-Dist: setuptools
